/*    */ package net.minecraft.block.properties;
/*    */ 
/*    */ import com.google.common.base.Predicate;
/*    */ import com.google.common.collect.ImmutableSet;
/*    */ import com.google.common.collect.Maps;
/*    */ import java.util.Collection;
/*    */ import java.util.Map;
/*    */ import net.minecraft.util.IStringSerializable;
/*    */ 
/*    */ 
/*    */ 
/*    */ 
/*    */ public class PropertyEnum<T extends Enum<T> & IStringSerializable>
/*    */   extends PropertyHelper<T>
/*    */ {
/*    */   private final ImmutableSet<T> allowedValues;
/* 17 */   private final Map<String, T> nameToValue = Maps.newHashMap();
/*    */   
/*    */   protected PropertyEnum(String name, Class<T> valueClass, Collection<T> allowedValues) {
/* 20 */     super(name, valueClass);
/* 21 */     this.allowedValues = ImmutableSet.copyOf(allowedValues);
/*    */     
/* 23 */     for (Enum enum_ : allowedValues) {
/* 24 */       String s = ((IStringSerializable)enum_).getName();
/*    */       
/* 26 */       if (this.nameToValue.containsKey(s)) {
/* 27 */         throw new IllegalArgumentException("Multiple values have the same name '" + s + "'");
/*    */       }
/*    */       
/* 30 */       this.nameToValue.put(s, (T)enum_);
/*    */     } 
/*    */   }
/*    */   
/*    */   public Collection<T> getAllowedValues() {
/* 35 */     return (Collection<T>)this.allowedValues;
/*    */   }
/*    */ 
/*    */ 
/*    */ 
/*    */   
/*    */   public String getName(T value) {
/* 42 */     return ((IStringSerializable)value).getName();
/*    */   }
/*    */   
/*    */   public static <T extends Enum<T> & IStringSerializable> PropertyEnum<T> create(String name, Class<T> clazz) {
/*    */     // Byte code:
/*    */     //   0: aload_0
/*    */     //   1: aload_1
/*    */     //   2: invokestatic alwaysTrue : ()Lcom/google/common/base/Predicate;
/*    */     //   5: invokestatic create : (Ljava/lang/String;Ljava/lang/Class;Lcom/google/common/base/Predicate;)Lnet/minecraft/block/properties/PropertyEnum;
/*    */     //   8: areturn
/*    */     // Line number table:
/*    */     //   Java source line number -> byte code offset
/*    */     //   #46	-> 0
/*    */     // Local variable table:
/*    */     //   start	length	slot	name	descriptor
/*    */     //   0	9	0	name	Ljava/lang/String;
/*    */     //   0	9	1	clazz	Ljava/lang/Class;
/*    */     // Local variable type table:
/*    */     //   start	length	slot	name	signature
/*    */     //   0	9	1	clazz	Ljava/lang/Class<TT;>;
/*    */   }
/*    */   
/*    */   public static <T extends Enum<T> & IStringSerializable> PropertyEnum<T> create(String name, Class<T> clazz, Predicate<T> filter) {
/*    */     // Byte code:
/*    */     //   0: aload_0
/*    */     //   1: aload_1
/*    */     //   2: aload_1
/*    */     //   3: invokevirtual getEnumConstants : ()[Ljava/lang/Object;
/*    */     //   6: checkcast [Ljava/lang/Enum;
/*    */     //   9: invokestatic newArrayList : ([Ljava/lang/Object;)Ljava/util/ArrayList;
/*    */     //   12: aload_2
/*    */     //   13: invokestatic filter : (Ljava/util/Collection;Lcom/google/common/base/Predicate;)Ljava/util/Collection;
/*    */     //   16: invokestatic create : (Ljava/lang/String;Ljava/lang/Class;Ljava/util/Collection;)Lnet/minecraft/block/properties/PropertyEnum;
/*    */     //   19: areturn
/*    */     // Line number table:
/*    */     //   Java source line number -> byte code offset
/*    */     //   #50	-> 0
/*    */     // Local variable table:
/*    */     //   start	length	slot	name	descriptor
/*    */     //   0	20	0	name	Ljava/lang/String;
/*    */     //   0	20	1	clazz	Ljava/lang/Class;
/*    */     //   0	20	2	filter	Lcom/google/common/base/Predicate;
/*    */     // Local variable type table:
/*    */     //   start	length	slot	name	signature
/*    */     //   0	20	1	clazz	Ljava/lang/Class<TT;>;
/*    */     //   0	20	2	filter	Lcom/google/common/base/Predicate<TT;>;
/*    */   }
/*    */   
/*    */   public static <T extends Enum<T> & IStringSerializable> PropertyEnum<T> create(String name, Class<T> clazz, Enum... values) {
/*    */     // Byte code:
/*    */     //   0: aload_0
/*    */     //   1: aload_1
/*    */     //   2: aload_2
/*    */     //   3: invokestatic newArrayList : ([Ljava/lang/Object;)Ljava/util/ArrayList;
/*    */     //   6: invokestatic create : (Ljava/lang/String;Ljava/lang/Class;Ljava/util/Collection;)Lnet/minecraft/block/properties/PropertyEnum;
/*    */     //   9: areturn
/*    */     // Line number table:
/*    */     //   Java source line number -> byte code offset
/*    */     //   #54	-> 0
/*    */     // Local variable table:
/*    */     //   start	length	slot	name	descriptor
/*    */     //   0	10	0	name	Ljava/lang/String;
/*    */     //   0	10	1	clazz	Ljava/lang/Class;
/*    */     //   0	10	2	values	[Ljava/lang/Enum;
/*    */     // Local variable type table:
/*    */     //   start	length	slot	name	signature
/*    */     //   0	10	1	clazz	Ljava/lang/Class<TT;>;
/*    */   }
/*    */   
/*    */   public static <T extends Enum<T> & IStringSerializable> PropertyEnum<T> create(String name, Class<T> clazz, Collection<T> values) {
/*    */     // Byte code:
/*    */     //   0: new net/minecraft/block/properties/PropertyEnum
/*    */     //   3: dup
/*    */     //   4: aload_0
/*    */     //   5: aload_1
/*    */     //   6: aload_2
/*    */     //   7: invokespecial <init> : (Ljava/lang/String;Ljava/lang/Class;Ljava/util/Collection;)V
/*    */     //   10: areturn
/*    */     // Line number table:
/*    */     //   Java source line number -> byte code offset
/*    */     //   #58	-> 0
/*    */     // Local variable table:
/*    */     //   start	length	slot	name	descriptor
/*    */     //   0	11	0	name	Ljava/lang/String;
/*    */     //   0	11	1	clazz	Ljava/lang/Class;
/*    */     //   0	11	2	values	Ljava/util/Collection;
/*    */     // Local variable type table:
/*    */     //   start	length	slot	name	signature
/*    */     //   0	11	1	clazz	Ljava/lang/Class<TT;>;
/*    */     //   0	11	2	values	Ljava/util/Collection<TT;>;
/*    */   }
/*    */ }


/* Location:              C:\User\\user\Desktop\Butteracking Client v4.1.jar!\net\minecraft\block\properties\PropertyEnum.class
 * Java compiler version: 8 (52.0)
 * JD-Core Version:       1.1.3
 */